pyrltools/__init__.py
pyrltools/external/rl_tools/include/rl_tools/containers.h
pyrltools/external/rl_tools/include/rl_tools/rl_tools.h
pyrltools/external/rl_tools/include/rl_tools/universe.h
pyrltools/external/rl_tools/include/rl_tools/version.h
pyrltools/external/rl_tools/include/rl_tools/containers/operations_arm.h
pyrltools/external/rl_tools/include/rl_tools/containers/operations_cpu.h
pyrltools/external/rl_tools/include/rl_tools/containers/operations_cpu_blas.h
pyrltools/external/rl_tools/include/rl_tools/containers/operations_cpu_mkl.h
pyrltools/external/rl_tools/include/rl_tools/containers/operations_cpu_openblas.h
pyrltools/external/rl_tools/include/rl_tools/containers/operations_cuda.h
pyrltools/external/rl_tools/include/rl_tools/containers/operations_dummy.h
pyrltools/external/rl_tools/include/rl_tools/containers/operations_esp32.h
pyrltools/external/rl_tools/include/rl_tools/containers/operations_generic.h
pyrltools/external/rl_tools/include/rl_tools/containers/persist.h
pyrltools/external/rl_tools/include/rl_tools/containers/persist_code.h
pyrltools/external/rl_tools/include/rl_tools/devices/arm.h
pyrltools/external/rl_tools/include/rl_tools/devices/cpu.h
pyrltools/external/rl_tools/include/rl_tools/devices/cpu_accelerate.h
pyrltools/external/rl_tools/include/rl_tools/devices/cpu_blas.h
pyrltools/external/rl_tools/include/rl_tools/devices/cpu_mkl.h
pyrltools/external/rl_tools/include/rl_tools/devices/cpu_openblas.h
pyrltools/external/rl_tools/include/rl_tools/devices/cpu_tensorboard.h
pyrltools/external/rl_tools/include/rl_tools/devices/cuda.h
pyrltools/external/rl_tools/include/rl_tools/devices/devices.h
pyrltools/external/rl_tools/include/rl_tools/devices/dummy.h
pyrltools/external/rl_tools/include/rl_tools/devices/esp32.h
pyrltools/external/rl_tools/include/rl_tools/devices/generic.h
pyrltools/external/rl_tools/include/rl_tools/logging/operations_arduino.h
pyrltools/external/rl_tools/include/rl_tools/logging/operations_arm.h
pyrltools-0.4.5.dist-info/METADATA
pyrltools-0.4.5.dist-info/WHEEL
pyrltools-0.4.5.dist-info/licenses/LICENSE
pyrltools-0.4.5.dist-info/RECORD
